{
    "blockly": false,
    "blockly_xml": "<xml></xml>",
    "category": "Uncategorized",
    "coa": {
        "data": {
            "description": "",
            "edges": [
                {
                    "id": "port_0_to_port_2",
                    "sourceNode": "0",
                    "sourcePort": "0_out",
                    "targetNode": "2",
                    "targetPort": "2_in"
                },
                {
                    "conditions": [
                        {
                            "index": 0
                        }
                    ],
                    "id": "port_2_to_port_3",
                    "sourceNode": "2",
                    "sourcePort": "2_out",
                    "targetNode": "3",
                    "targetPort": "3_in"
                }
            ],
            "hash": "4d1cdb79ff7fc78e17dda68b1b07e653bd9f06de",
            "nodes": {
                "0": {
                    "data": {
                        "advanced": {
                            "join": []
                        },
                        "functionName": "on_start",
                        "id": "0",
                        "type": "start"
                    },
                    "errors": {},
                    "id": "0",
                    "type": "start",
                    "warnings": {},
                    "x": 1205,
                    "y": 419.9999999999999
                },
                "1": {
                    "data": {
                        "advanced": {
                            "join": []
                        },
                        "functionName": "on_finish",
                        "id": "1",
                        "type": "end"
                    },
                    "errors": {},
                    "id": "1",
                    "type": "end",
                    "warnings": {},
                    "x": 1200,
                    "y": 1040
                },
                "2": {
                    "data": {
                        "advanced": {
                            "customName": "filter artifacts pending_scan",
                            "customNameId": 0,
                            "join": []
                        },
                        "conditions": [
                            {
                                "comparisons": [
                                    {
                                        "conditionIndex": 0,
                                        "op": "in",
                                        "param": "pending_scan",
                                        "value": "artifact:*.tags"
                                    }
                                ],
                                "conditionIndex": 0,
                                "customName": "pending_scan",
                                "logic": "and"
                            }
                        ],
                        "functionId": 1,
                        "functionName": "filter_artifacts_pending_scan",
                        "id": "2",
                        "type": "filter"
                    },
                    "errors": {},
                    "id": "2",
                    "type": "filter",
                    "warnings": {},
                    "x": 1240,
                    "y": 580
                },
                "3": {
                    "data": {
                        "action": "get report",
                        "actionType": "investigate",
                        "advanced": {
                            "customName": "get scann report",
                            "customNameId": 0,
                            "join": []
                        },
                        "connector": "VirusTotal v3",
                        "connectorConfigs": [
                            "virustotal"
                        ],
                        "connectorId": "3fe4875d-a4a7-47d3-9ef1-f9e63a6653a4",
                        "connectorVersion": "v1",
                        "functionId": 1,
                        "functionName": "get_scann_report",
                        "id": "3",
                        "parameters": {
                            "scan_id": "filtered-data:filter_artifacts_pending_scan:condition_1:artifact:*.cef.scan_id",
                            "wait_time": "1"
                        },
                        "requiredParameters": [
                            {
                                "data_type": "string",
                                "field": "scan_id"
                            }
                        ],
                        "type": "action"
                    },
                    "errors": {},
                    "id": "3",
                    "type": "action",
                    "warnings": {},
                    "x": 1190,
                    "y": 744.5
                }
            },
            "notes": ""
        },
        "input_spec": null,
        "output_spec": null,
        "playbook_type": "automation",
        "python_version": "3",
        "schema": "5.0.10",
        "version": "6.1.1.211"
    },
    "create_time": "2023-11-28T21:25:08.930468+00:00",
    "draft_mode": false,
    "labels": [
        "*"
    ],
    "tags": []
}